ngpa/__init__.py
ngpa/lib.py
ngpa/ngpa.py
ngpa-0.0.6.dist-info/METADATA
ngpa-0.0.6.dist-info/WHEEL
ngpa-0.0.6.dist-info/entry_points.txt
ngpa-0.0.6.dist-info/licenses/LICENSE
ngpa-0.0.6.dist-info/RECORD
