Metadata-Version: 2.1
Name: ngpa
Version: 0.0.6
Summary: Some handy functions for computing NJU gpa
Project-URL: Homepage, https://github.com/UshioA/ngpa
Project-URL: Bug Track, https://github.com/UshioA/ngpa/issues
Author-email: DingZhen <realdingzhen@outlook.com>
License:                    GNU LESSER GENERAL PUBLIC LICENSE
License-File: LICENSE
Keywords: NJU,gpa
Classifier: License :: OSI Approved :: GNU Lesser General Public License v3 (LGPLv3)
Classifier: Operating System :: OS Independent
Classifier: Programming Language :: Python :: 3
Requires-Python: >=3.6
